request_token/__init__.py
request_token/admin.py
request_token/apps.py
request_token/context_processors.py
request_token/decorators.py
request_token/exceptions.py
request_token/middleware.py
request_token/migrations/0001_initial.py
request_token/migrations/0002_auto_20151227_1428.py
request_token/migrations/0003_auto_20151229_1105.py
request_token/migrations/0004_remove_requesttoken_target_url.py
request_token/migrations/0005_auto_20160103_1655.py
request_token/migrations/0006_auto_20161104_1428.py
request_token/migrations/0007_add_client_ipv6.py
request_token/migrations/0008_convert_token_data_to_jsonfield.py
request_token/migrations/0009_requesttokenerror.py
request_token/migrations/0010_auto_20170521_1944.py
request_token/migrations/0011_update_model_meta_options.py
request_token/migrations/__init__.py
request_token/models.py
request_token/settings.py
request_token/templatetags/__init__.py
request_token/templatetags/request_token_tags.py
request_token/utils.py
request_token-0.10.dist-info/LICENSE
request_token-0.10.dist-info/WHEEL
request_token-0.10.dist-info/METADATA
request_token-0.10.dist-info/RECORD
