Metadata-Version: 2.1
Name: request-token
Version: 0.10
Summary: JWT-backed Django app for managing querystring tokens.
Home-page: https://github.com/yunojuno/django-request-token
License: MIT
Author: YunoJuno
Author-email: code@yunojuno.com
Maintainer: YunoJuno
Maintainer-email: code@yunojuno.com
Requires-Python: >=3.7,<4.0
Classifier: Environment :: Web Environment
Classifier: Framework :: Django :: 2.2
Classifier: Framework :: Django :: 3.0
Classifier: License :: OSI Approved :: MIT License
Classifier: Operating System :: OS Independent
Classifier: Programming Language :: Python :: 3
Classifier: Programming Language :: Python :: 3 :: Only
Classifier: Programming Language :: Python :: 3.7
Classifier: Programming Language :: Python :: 3.8
Requires-Dist: django (>=2.2,<4.0)
Requires-Dist: psycopg2-binary
Requires-Dist: pyjwt
Requires-Dist: sqlparse
Project-URL: Repository, https://github.com/yunojuno/django-request-token
